package_590015053/__init__.py
package_590015053/operations.py
package_590015053-0.1.0.dist-info/METADATA
package_590015053-0.1.0.dist-info/WHEEL
package_590015053-0.1.0.dist-info/top_level.txt
package_590015053-0.1.0.dist-info/RECORD
