Metadata-Version: 2.4
Name: package_590015053
Version: 0.1.0
Summary: A sample package for testing purposes
Author: Krish Mishra
Dynamic: author
Dynamic: summary
